{
    "dokumente": {
        "$": {
            "builddate": "20231128213544",
            "doknr": "BJNR140600994"
        },
        "norm": [
            {
                "$": {
                    "builddate": "20231128213544",
                    "doknr": "BJNR140600994"
                },
                "metadaten": [
                    {
                        "jurabk": [
                            "GleichberG 2"
                        ],
                        "amtabk": [
                            "2. GleiBG"
                        ],
                        "ausfertigung-datum": [
                            {
                                "_": "1994-06-24",
                                "$": {
                                    "manuell": "ja"
                                }
                            }
                        ],
                        "fundstelle": [
                            {
                                "$": {
                                    "typ": "amtlich"
                                },
                                "periodikum": [
                                    "BGBl I"
                                ],
                                "zitstelle": [
                                    "1994, 1406 (2103)"
                                ]
                            }
                        ],
                        "kurzue": [
                            "Zweites Gleichberechtigungsgesetz"
                        ],
                        "langue": [
                            "Gesetz zur Durchsetzung der Gleichberechtigung von Frauen und Männern"
                        ]
                    }
                ],
                "textdaten": [
                    {
                        "text": [
                            {
                                "$": {
                                    "format": "XML"
                                },
                                "Content": [
                                    {
                                        "P": [
                                            ""
                                        ]
                                    }
                                ]
                            }
                        ],
                        "fussnoten": [
                            {
                                "Content": [
                                    {
                                        "P": [
                                            {
                                                "_": "(+++ Textnachweis ab:  1. 9.1994 +++)  Art. 1: FFöG 205-1-1 Art. 2 bis 9: Änderungsvorschriften Art. 10: BSchG 8054-1 Art. 11: BGremBG 116-1 Art. 12: Übergangsregelung Art. 13: Inkrafttreten",
                                                "BR": [
                                                    "",
                                                    "",
                                                    "",
                                                    "",
                                                    "",
                                                    "",
                                                    ""
                                                ]
                                            }
                                        ]
                                    }
                                ]
                            }
                        ]
                    }
                ]
            },
            {
                "$": {
                    "builddate": "20231128213544",
                    "doknr": "BJNR140600994BJNE000100307"
                },
                "metadaten": [
                    {
                        "jurabk": [
                            "GleichberG 2"
                        ],
                        "enbez": [
                            "Art 1"
                        ],
                        "titel": [
                            {
                                "_": "Gesetz zur Förderung von Frauen und der Vereinbarkeit\nvon Familie und Beruf in der Bundesverwaltung und den\nGerichten des Bundes (Frauenfördergesetz - FFG)",
                                "$": {
                                    "format": "parat"
                                }
                            }
                        ]
                    }
                ],
                "textdaten": [
                    {
                        "text": [
                            {
                                "$": {
                                    "format": "XML"
                                },
                                "Content": [
                                    {
                                        "P": [
                                            "-"
                                        ]
                                    }
                                ]
                            }
                        ],
                        "fussnoten": [
                            ""
                        ]
                    }
                ]
            },
            {
                "$": {
                    "builddate": "20231128213544",
                    "doknr": "BJNR140600994BJNE000200307"
                },
                "metadaten": [
                    {
                        "jurabk": [
                            "GleichberG 2"
                        ],
                        "enbez": [
                            "(XXXX) Art 2 bis Art 9"
                        ],
                        "titel": [
                            {
                                "_": "(weggefallen)",
                                "$": {
                                    "format": "XML"
                                }
                            }
                        ]
                    }
                ],
                "textdaten": [
                    {
                        "text": [
                            {
                                "$": {
                                    "format": "XML"
                                },
                                "Content": [
                                    {
                                        "P": [
                                            "-"
                                        ]
                                    }
                                ]
                            }
                        ],
                        "fussnoten": [
                            ""
                        ]
                    }
                ]
            },
            {
                "$": {
                    "builddate": "20231128213544",
                    "doknr": "BJNR140600994BJNE000300307"
                },
                "metadaten": [
                    {
                        "jurabk": [
                            "GleichberG 2"
                        ],
                        "enbez": [
                            "Art 10"
                        ],
                        "titel": [
                            {
                                "_": "Gesetz zum Schutz der Beschäftigten vor sexueller\nBelästigung am Arbeitsplatz (Beschäftigtenschutzgesetz)",
                                "$": {
                                    "format": "parat"
                                }
                            }
                        ]
                    }
                ],
                "textdaten": [
                    {
                        "text": [
                            {
                                "$": {
                                    "format": "XML"
                                },
                                "Content": [
                                    {
                                        "P": [
                                            "-"
                                        ]
                                    }
                                ]
                            }
                        ],
                        "fussnoten": [
                            ""
                        ]
                    }
                ]
            },
            {
                "$": {
                    "builddate": "20231128213544",
                    "doknr": "BJNR140600994BJNE000400307"
                },
                "metadaten": [
                    {
                        "jurabk": [
                            "GleichberG 2"
                        ],
                        "enbez": [
                            "Art 11"
                        ],
                        "titel": [
                            {
                                "_": "Gesetz über die Berufung und Entsendung von\nFrauen und Männern in Gremien im Einflußbereich des\nBundes (Bundesgremienbesetzungsgesetz - BGremBG)",
                                "$": {
                                    "format": "parat"
                                }
                            }
                        ]
                    }
                ],
                "textdaten": [
                    {
                        "text": [
                            {
                                "$": {
                                    "format": "XML"
                                },
                                "Content": [
                                    {
                                        "P": [
                                            "-"
                                        ]
                                    }
                                ]
                            }
                        ],
                        "fussnoten": [
                            ""
                        ]
                    }
                ]
            },
            {
                "$": {
                    "builddate": "20231128213544",
                    "doknr": "BJNR140600994BJNE000500307"
                },
                "metadaten": [
                    {
                        "jurabk": [
                            "GleichberG 2"
                        ],
                        "enbez": [
                            "Art 12"
                        ],
                        "titel": [
                            {
                                "_": "Übergangsregelung",
                                "$": {
                                    "format": "parat"
                                }
                            }
                        ]
                    }
                ],
                "textdaten": [
                    {
                        "text": [
                            {
                                "$": {
                                    "format": "XML"
                                },
                                "Content": [
                                    {
                                        "P": [
                                            {
                                                "_": "Für die Artikel 7 und 8 gilt folgende Übergangsregelung: ",
                                                "DL": [
                                                    {
                                                        "$": {
                                                            "Font": "normal",
                                                            "Type": "arabic"
                                                        },
                                                        "DT": [
                                                            "1.",
                                                            "2."
                                                        ],
                                                        "DD": [
                                                            {
                                                                "$": {
                                                                    "Font": "normal"
                                                                },
                                                                "LA": [
                                                                    {
                                                                        "_": "In Fällen, in denen der Arbeitgeber vor dem 1. September 1994 gegen das Benachteiligungsverbot des § 611a Abs. 1 des Bürgerlichen Gesetzbuchs verstoßen hat, ist § 61b des Arbeitsgerichtsgesetzes nicht anzuwenden.",
                                                                        "$": {
                                                                            "Size": "normal"
                                                                        }
                                                                    }
                                                                ]
                                                            },
                                                            {
                                                                "$": {
                                                                    "Font": "normal"
                                                                },
                                                                "LA": [
                                                                    {
                                                                        "_": "Bei der Berechnung der in § 611a Abs. 4 des Bürgerlichen Gesetzbuchs bestimmten Frist bleiben Zeiten vor dem 1. September 1994 außer Betracht.",
                                                                        "$": {
                                                                            "Size": "normal"
                                                                        }
                                                                    }
                                                                ]
                                                            }
                                                        ]
                                                    }
                                                ]
                                            }
                                        ]
                                    }
                                ]
                            }
                        ]
                    }
                ]
            },
            {
                "$": {
                    "builddate": "20231128213544",
                    "doknr": "BJNR140600994BJNE000600307"
                },
                "metadaten": [
                    {
                        "jurabk": [
                            "GleichberG 2"
                        ],
                        "enbez": [
                            "Art 13"
                        ],
                        "titel": [
                            {
                                "_": "Inkrafttreten",
                                "$": {
                                    "format": "parat"
                                }
                            }
                        ]
                    }
                ],
                "textdaten": [
                    {
                        "text": [
                            {
                                "$": {
                                    "format": "XML"
                                },
                                "Content": [
                                    {
                                        "P": [
                                            "Dieses Gesetz tritt am 1. September 1994 in Kraft."
                                        ]
                                    }
                                ]
                            }
                        ]
                    }
                ]
            }
        ]
    }
}